kfp_local/__init__.py
kfp_local/_dag.py
kfp_local/_local_client.py
kfp_local/_version.py
kfp_local/local_client_test.py
kfp_local-1.1.0.dist-info/LICENSE
kfp_local-1.1.0.dist-info/METADATA
kfp_local-1.1.0.dist-info/WHEEL
kfp_local-1.1.0.dist-info/top_level.txt
kfp_local-1.1.0.dist-info/RECORD
