Metadata-Version: 2.1
Name: kfp-local
Version: 1.1.0
Summary: kfp local client runs pipelines on local host or in docker container
License: UNKNOWN
Keywords: kubeflow,kfp,local
Platform: UNKNOWN
Requires-Python: >=3.7
License-File: LICENSE
Requires-Dist: kfp (<2.0,>=1.8.12)
